django_logmancer-0.1.3.dist-info/licenses/LICENSE
docs/source/conf.py
logmancer/__init__.py
logmancer/admin.py
logmancer/apps.py
logmancer/conf.py
logmancer/levels.py
logmancer/middleware.py
logmancer/models.py
logmancer/signals.py
logmancer/utils.py
logmancer/management/__init__.py
logmancer/management/commands/__init__.py
logmancer/management/commands/logmancer_cleanup.py
logmancer/management/commands/test_notifications.py
logmancer/notifications/__init__.py
logmancer/notifications/base.py
logmancer/notifications/email.py
logmancer/notifications/manager.py
logmancer/notifications/slack.py
logmancer/notifications/telegram.py
django_logmancer-0.1.3.dist-info/METADATA
django_logmancer-0.1.3.dist-info/WHEEL
django_logmancer-0.1.3.dist-info/top_level.txt
django_logmancer-0.1.3.dist-info/RECORD
