Metadata-Version: 2.4
Name: django-logmancer
Version: 0.1.3
Summary: Advanced logging and monitoring for Django applications
Author-email: Abdulsamet TATAR <abdulsamettatar@gmail.com>
License-Expression: MIT
Project-URL: Homepage, https://github.com/abdulsamet/logmancer
Project-URL: Repository, https://github.com/abdulsamet/logmancer
Project-URL: Issues, https://github.com/abdulsamet/logmancer/issues
Keywords: django,logging,monitoring,middleware,signals
Classifier: Development Status :: 4 - Beta
Classifier: Environment :: Web Environment
Classifier: Framework :: Django
Classifier: Framework :: Django :: 4.2
Classifier: Framework :: Django :: 5.0
Classifier: Framework :: Django :: 5.1
Classifier: Framework :: Django :: 5.2
Classifier: Intended Audience :: Developers
Classifier: Operating System :: OS Independent
Classifier: Programming Language :: Python :: 3
Classifier: Programming Language :: Python :: 3.10
Classifier: Programming Language :: Python :: 3.11
Classifier: Programming Language :: Python :: 3.12
Classifier: Programming Language :: Python :: 3.13
Classifier: Topic :: Internet :: WWW/HTTP
Classifier: Topic :: Software Development :: Libraries :: Python Modules
Classifier: Topic :: System :: Logging
Requires-Python: >=3.10
License-File: LICENSE
Requires-Dist: Django>=4.2
Provides-Extra: dev
Requires-Dist: pytest>=7.0; extra == "dev"
Requires-Dist: pytest-django>=4.5; extra == "dev"
Requires-Dist: pytest-cov; extra == "dev"
Requires-Dist: pytest-mock; extra == "dev"
Requires-Dist: tox-uv>=1.27.0; extra == "dev"
Requires-Dist: factory-boy; extra == "dev"
Requires-Dist: freezegun; extra == "dev"
Requires-Dist: black>=23.0; extra == "dev"
Requires-Dist: isort>=5.12; extra == "dev"
Requires-Dist: flake8>=6.0; extra == "dev"
Requires-Dist: mypy>=1.0; extra == "dev"
Requires-Dist: django-stubs; extra == "dev"
Requires-Dist: bandit[toml]; extra == "dev"
Requires-Dist: safety; extra == "dev"
Dynamic: license-file
